README.rst
setup.py
cwcli/__init__.py
cwcli/meta.py
cwcli.egg-info/PKG-INFO
cwcli.egg-info/SOURCES.txt
cwcli.egg-info/dependency_links.txt
cwcli.egg-info/entry_points.txt
cwcli.egg-info/requires.txt
cwcli.egg-info/top_level.txt
cwcli/commands/__init__.py
cwcli/commands/company/__init__.py
cwcli/commands/company/get.py
cwcli/lib/__init__.py
cwcli/lib/connectwise/__init__.py
cwcli/lib/connectwise/common.py
cwcli/lib/connectwise/company_api/__init__.py
cwcli/lib/connectwise/company_api/api.py
cwcli/lib/connectwise/transformer/__init__.py
cwcli/lib/connectwise/transformer/json_transformer.py
cwcli/lib/environment/__init__.py
cwcli/lib/environment/rc_parser.py